<model>
    <instance>
        <rencana_persalinan id="rencana_persalinan" version="201503240220">
          <formhub>
            <uuid/>
          </formhub>
          <B01036/>
          <B01037/>
          <B01038/>
          <B01039/>
          <B01040/>
          <B01041/>
          <B01042/>
          <B01043/>
          <B01044/>
          <B01045/>
          <B01046/>
          <B01047/>
          <B01048/>
          <B01049/>
          <B01050/>
          <B01051/>
          <B01052/>
          <B01053/>
          <B01054/>
          <B01055/>
          <B01056/>
          <B01057/>
          <B01058/>
          <beratjaninnote/>
          <B01059/>
          <B01060/>
          <B01061/>
          <B01062/>
          <B01063/>
          <B01064/>
          <B01065/>
          <B01066/>
          <B01067/>
          <B01068/>
          <B01069/>
          <B01070/>
          <B01071/>
          <B01072/>
          <B01073/>
          <B01074/>
          <B01075/>
          <B01076/>
          <B01077/>
          <B01078/>
          <B01079/>
          <B01080/>
          <B01081/>
          <B01082/>
          <B01083/>
          <B01084/>
          <B01085/>
          <B01086/>
          <B01087/>
          <B01088/>
          <B01089/>
          <B01090/>
          <B01091/>
          <meta>
            <instanceID/>
          </meta>
        </rencana_persalinan>
      </instance>
  </model>